brainsync_sdk-0.1.0.dist-info/METADATA
brainsync_sdk-0.1.0.dist-info/WHEEL
brainsync_sdk/__init__.pyi
brainsync_sdk/__init__.py
brainsync_sdk/README.md
brainsync_sdk/__init__.pyi.template
brainsync_sdk/_native.pyi
brainsync_sdk/_native.abi3.so
brainsync_sdk-0.1.0.dist-info/RECORD
